basicsr/__init__.py
basicsr/test.py
basicsr/train.py
basicsr/version.py
basicsr/archs/__init__.py
basicsr/archs/arch_util.py
basicsr/archs/basicvsr_arch.py
basicsr/archs/basicvsrpp_arch.py
basicsr/archs/dfdnet_arch.py
basicsr/archs/dfdnet_util.py
basicsr/archs/discriminator_arch.py
basicsr/archs/duf_arch.py
basicsr/archs/ecbsr_arch.py
basicsr/archs/edsr_arch.py
basicsr/archs/edvr_arch.py
basicsr/archs/hifacegan_arch.py
basicsr/archs/hifacegan_util.py
basicsr/archs/inception.py
basicsr/archs/rcan_arch.py
basicsr/archs/ridnet_arch.py
basicsr/archs/rrdbnet_arch.py
basicsr/archs/spynet_arch.py
basicsr/archs/srresnet_arch.py
basicsr/archs/srvgg_arch.py
basicsr/archs/stylegan2_arch.py
basicsr/archs/stylegan2_bilinear_arch.py
basicsr/archs/swinir_arch.py
basicsr/archs/tof_arch.py
basicsr/archs/vgg_arch.py
basicsr/data/__init__.py
basicsr/data/data_sampler.py
basicsr/data/data_util.py
basicsr/data/degradations.py
basicsr/data/ffhq_dataset.py
basicsr/data/paired_image_dataset.py
basicsr/data/prefetch_dataloader.py
basicsr/data/realesrgan_dataset.py
basicsr/data/realesrgan_paired_dataset.py
basicsr/data/reds_dataset.py
basicsr/data/single_image_dataset.py
basicsr/data/transforms.py
basicsr/data/video_test_dataset.py
basicsr/data/vimeo90k_dataset.py
basicsr/losses/__init__.py
basicsr/losses/basic_loss.py
basicsr/losses/gan_loss.py
basicsr/losses/loss_util.py
basicsr/metrics/__init__.py
basicsr/metrics/fid.py
basicsr/metrics/metric_util.py
basicsr/metrics/niqe.py
basicsr/metrics/niqe_pris_params.npz
basicsr/metrics/psnr_ssim.py
basicsr/models/__init__.py
basicsr/models/base_model.py
basicsr/models/edvr_model.py
basicsr/models/esrgan_model.py
basicsr/models/hifacegan_model.py
basicsr/models/lr_scheduler.py
basicsr/models/realesrgan_model.py
basicsr/models/realesrnet_model.py
basicsr/models/sr_model.py
basicsr/models/srgan_model.py
basicsr/models/stylegan2_model.py
basicsr/models/swinir_model.py
basicsr/models/video_base_model.py
basicsr/models/video_gan_model.py
new_basicsr-1.0.0.dist-info/LICENSE.txt
new_basicsr-1.0.0.dist-info/METADATA
new_basicsr-1.0.0.dist-info/WHEEL
new_basicsr-1.0.0.dist-info/top_level.txt
new_basicsr-1.0.0.dist-info/RECORD
