Metadata-Version: 2.1
Name: new-basicsr
Version: 1.0.0
Summary: This project was forked from https://github.com/XPixelGroup/BasicSR. Seems like it is not maintained anymore. I will try to maintain it and add new features. I will also try to keep it up to date with the latest PyTorch versions
Home-page: https://github.com/MinasFakhori/BasicSR
Author: Minas
Author-email: minas.fakhori4@gmail.com
License: Apache License 2.0
Keywords: computer vision,restoration,super resolution
Classifier: Development Status :: 4 - Beta
Classifier: License :: OSI Approved :: Apache Software License
Classifier: Operating System :: OS Independent
Classifier: Programming Language :: Python :: 3
Classifier: Programming Language :: Python :: 3.7
Classifier: Programming Language :: Python :: 3.8
License-File: LICENSE.txt
Requires-Dist: addict
Requires-Dist: future
Requires-Dist: lmdb
Requires-Dist: numpy >=1.17
Requires-Dist: opencv-python
Requires-Dist: Pillow
Requires-Dist: pyyaml
Requires-Dist: requests
Requires-Dist: scikit-image
Requires-Dist: scipy
Requires-Dist: tb-nightly
Requires-Dist: torch >=1.7
Requires-Dist: torchvision
Requires-Dist: tqdm
Requires-Dist: yapf
